[
  {
    "id": "1780990482513821749",
    "name": "李老师不是你老师",
    "createdDate": "2024-04-19 00:03:14",
    "content": "On April 18, Guilin University of Electronic Technology forced Chinese students to move to the old dormitory building with poor conditions.\nThe original dormitory building was vacated for international students to live in.\nThe school compensated each student 50 yuan.",
    "images": "/tweet/image/whyyoutouzhele/2024/04/19/1780990482513821749_0.jpg,/tweet/image/whyyoutouzhele/2024/04/19/1780990482513821749_1.jpg,/tweet/image/whyyoutouzhele/2024/04/19/1780990482513821749_2.jpg,/tweet/image/whyyoutouzhele/2024/04/19/1780990482513821749_3.jpg,",
    "videos": "",
    "hasFullContentTranslated": true,
    "hasPublished": true
  },
  {
    "id": "1781093902797168643",
    "name": "李老师不是你老师",
    "createdDate": "2024-04-19 06:54:12",
    "content": "@nict570npc Then you are welcome to check every one of my posts and point out any problems. I will accept them humbly.",
    "images": "",
    "videos": "",
    "hasFullContentTranslated": true,
    "hasPublished": true
  },
  {
    "id": "1781255406909554997",
    "name": "李老师不是你老师",
    "createdDate": "2024-04-19 17:35:57",
    "content": "On April 19, it was reported online that an accident occurred during a test run on Xi'an Metro Line 10.",
    "images": "/tweet/image/whyyoutouzhele/2024/04/19/1781255406909554997_0.jpg,/tweet/image/whyyoutouzhele/2024/04/19/1781255406909554997_1.jpg,/tweet/image/whyyoutouzhele/2024/04/19/1781255406909554997_2.jpg,",
    "videos": "",
    "hasFullContentTranslated": true,
    "hasPublished": true
  },
  {
    "id": "1781264112124666240",
    "name": "李老师不是你老师",
    "createdDate": "2024-04-19 18:10:33",
    "content": "On April 19, the Beijing Half Marathon Organizing Committee announced the investigation and handling decision on the results of the men's race.\nThe article stated that several foreign runners in the video were \"pacemakers\", but Xtep did not clearly mark the pacemakers, resulting in several people participating in the race with athlete numbers.",
    "images": "/tweet/image/whyyoutouzhele/2024/04/19/1781264112124666240_0.jpg,/tweet/image/whyyoutouzhele/2024/04/19/1781264112124666240_1.jpg,/tweet/image/whyyoutouzhele/2024/04/19/1781264112124666240_2.jpg,",
    "videos": "",
    "hasFullContentTranslated": true,
    "hasPublished": true
  },
  {
    "id": "1781279291910627333",
    "name": "李老师不是你老师",
    "createdDate": "2024-04-19 19:10:52",
    "content": "On April 19, the PLA established the Information Support Force, which is directly led and commanded by the Central Military Commission.",
    "images": "/tweet/image/whyyoutouzhele/2024/04/19/1781279291910627333_0.jpg,",
    "videos": "",
    "hasFullContentTranslated": true,
    "hasPublished": true
  },
  {
    "id": "1781286287351152660",
    "name": "李老师不是你老师",
    "createdDate": "2024-04-19 19:38:40",
    "content": "A Xiaohongshu netizen said that due to the strict crackdown on illegal overseas work, the entry and exit ports of Chengdu Airport have become extremely strict.",
    "images": "/tweet/image/whyyoutouzhele/2024/04/19/1781286287351152660_0.jpg,/tweet/image/whyyoutouzhele/2024/04/19/1781286287351152660_1.jpg,/tweet/image/whyyoutouzhele/2024/04/19/1781286287351152660_2.jpg,/tweet/image/whyyoutouzhele/2024/04/19/1781286287351152660_3.jpg,",
    "videos": "",
    "hasFullContentTranslated": true,
    "hasPublished": true
  },
  {
    "id": "1781313417266999424",
    "name": "李老师不是你老师",
    "createdDate": "2024-04-19 21:26:28",
    "content": "On April 19, the spokesperson of the Ministry of Foreign Affairs expressed firm opposition to Japan's launch of the fifth round of Fukushima nuclear wastewater discharge into the sea. However, this matter seems to have been cooled down by the platform.\nIn addition, today is the day when Japan's nuclear wastewater officially arrives at the coast of my country.",
    "images": "/tweet/image/whyyoutouzhele/2024/04/19/1781313417266999424_0.jpg,/tweet/image/whyyoutouzhele/2024/04/19/1781313417266999424_1.jpg,",
    "videos": "",
    "hasFullContentTranslated": true,
    "hasPublished": true
  },
  {
    "id": "1781322538372452425",
    "name": "李老师不是你老师",
    "createdDate": "2024-04-19 22:02:43",
    "content": "Following Chongqing, netizens in Chengdu, Changzhou, Hefei, Nanchang and other places have reported a surge in gas bills at home.",
    "images": "/tweet/image/whyyoutouzhele/2024/04/19/1781322538372452425_0.jpg,/tweet/image/whyyoutouzhele/2024/04/19/1781322538372452425_1.jpg,/tweet/image/whyyoutouzhele/2024/04/19/1781322538372452425_2.jpg,/tweet/image/whyyoutouzhele/2024/04/19/1781322538372452425_3.jpg,",
    "videos": "",
    "hasFullContentTranslated": true,
    "hasPublished": true
  },
  {
    "id": "1781340809633161403",
    "name": "李老师不是你老师",
    "createdDate": "2024-04-19 23:15:19",
    "content": "On April 17, the Hong Kong Special Administrative Region Government Security Bureau issued a message stating that since the Hong Kong National Security Law came into effect, as of March 8, a total of 291 people have been arrested by the Police Force for suspected acts and activities endangering national security, ranging in age from 15 to 90 years old.",
    "images": "/tweet/image/whyyoutouzhele/2024/04/19/1781340809633161403_0.jpg,",
    "videos": "",
    "hasFullContentTranslated": true,
    "hasPublished": true
  },
  {
    "id": "1781348167134453841",
    "name": "李老师不是你老师",
    "createdDate": "2024-04-19 23:44:33",
    "content": "\"Eat Chicken Tonight\"\nApril 18, Jingdezhen Health School, Jiangxi Province.\nBecause the school security guards did not allow the vendors to set up stalls at the school gate and tore off the payment code posted on the stalls, the two sides had a dispute.\nThe vendor was furious and threw all the chicken legs he sold into the school, causing students to scramble for them",
    "images": "",
    "videos": "/tweet/video/whyyoutouzhele/2024/04/19/1781348167134453841_0.jpg,",
    "hasFullContentTranslated": true,
    "hasPublished": true
  },
  {
    "id": "1781348321413451818",
    "name": "李老师不是你老师",
    "createdDate": "2024-04-19 23:45:10",
    "content": "On the afternoon of April 19, Jingdezhen Health School issued a notice: At around 21:00 on April 18, when our students were returning to the dormitory after evening self-study, they passed by the walled section along the street. Mobile vendors outside the wall took the opportunity to hawk their wares and had an argument with our school’s order maintenance staff. They threw food into the wall, causing students to gather to catch the food. Next, our school will learn from this incident, strengthen campus management, and further enrich the meals in the school cafeteria on the basis of ensuring food safety.",
    "images": "/tweet/image/whyyoutouzhele/2024/04/19/1781348321413451818_0.jpg,",
    "videos": "",
    "hasFullContentTranslated": true,
    "hasPublished": true
  },
  {
    "id": "1781349281187631257",
    "name": "李老师不是你老师",
    "createdDate": "2024-04-19 23:48:59",
    "content": "Subsequent update\nOn the evening of the 19th, a Xi'an Metro employee said it was a train collision test, not the accident reported online.",
    "images": "/tweet/image/whyyoutouzhele/2024/04/19/1781349281187631257_0.jpg,",
    "videos": "",
    "hasFullContentTranslated": true,
    "hasPublished": true
  }
]