[{"id":"1820130866724852119","name":"李老师不是你老师","accountId":"whyyoutouzhele","sensitive":false,"createdDate":"2024-08-05 00:13:09","content":"https://t.co/AvGhOUlARk","images":"/tweet/image/whyyoutouzhele/2024/08/05/1820130866724852119_0.jpg,","videos":"","hasPublished":true},{"id":"1820137979580748201","name":"李老师不是你老师","accountId":"whyyoutouzhele","sensitive":false,"createdDate":"2024-08-05 00:41:25","content":"台湾の観客は「青い空、白い太陽、すべての地面は赤い」を歌った","images":"","videos":"/tweet/video/whyyoutouzhele/2024/08/05/1820137979580748201_0.jpg,","hasFullContentTranslated":true,"hasPublished":true},{"id":"1820153886889640036","name":"李老师不是你老师","accountId":"whyyoutouzhele","sensitive":false,"createdDate":"2024-08-05 01:44:38","content":"8月4日、パリオリンピックのバドミントン男子ダブルス決勝で台湾選手が金メダルを獲得し、会場では中華台北国旗がゆっくりと掲げられ、多くの台湾人が中華民国の国旗歌を合唱した。\n 中国のネットユーザーらは「台湾が勝てば中国が勝つ」「関係ない。1位も2位も中国のものだ」と反応した。\n ","images":"/tweet/image/whyyoutouzhele/2024/08/05/1820153886889640036_0.jpg,/tweet/image/whyyoutouzhele/2024/08/05/1820153886889640036_1.jpg,/tweet/image/whyyoutouzhele/2024/08/05/1820153886889640036_2.jpg,","videos":"/tweet/video/whyyoutouzhele/2024/08/05/1820153886889640036_0.jpg,","hasFullContentTranslated":true,"hasPublished":true},{"id":"1820165609386377289","name":"李老师不是你老师","accountId":"whyyoutouzhele","sensitive":false,"createdDate":"2024-08-05 02:31:12","content":"台湾の人々はこの瞬間を祝います","images":"","videos":"/tweet/video/whyyoutouzhele/2024/08/05/1820165609386377289_0.jpg,/tweet/video/whyyoutouzhele/2024/08/05/1820165609386377289_1.jpg,","hasFullContentTranslated":true,"hasPublished":true},{"id":"1820256482132136138","name":"李老师不是你老师","accountId":"whyyoutouzhele","sensitive":false,"createdDate":"2024-08-05 08:32:18","content":"8月4日、メディアは武漢市の有名な不動産プロジェクトである万和光学谷の単価が登録時の2万元強から1万2500元に半減されたと報じた。 ","images":"/tweet/image/whyyoutouzhele/2024/08/05/1820256482132136138_0.jpg,","videos":"","hasFullContentTranslated":true,"hasPublished":true},{"id":"1820259847134384227","name":"李老师不是你老师","accountId":"whyyoutouzhele","sensitive":false,"createdDate":"2024-08-05 08:45:41","content":"四川省蘆州市","images":"/tweet/image/whyyoutouzhele/2024/08/05/1820259847134384227_0.jpg,","videos":"","hasFullContentTranslated":true,"hasPublished":true},{"id":"1820377932864606706","name":"李老师不是你老师","accountId":"whyyoutouzhele","sensitive":false,"createdDate":"2024-08-05 16:34:54","content":"現時点では、郡党書記や郡判事に立候補したいブロガーが投稿した動画はすべて削除されている。\n ","images":"/tweet/image/whyyoutouzhele/2024/08/05/1820377932864606706_0.jpg,","videos":"","hasFullContentTranslated":true,"hasPublished":true},{"id":"1820386404360446382","name":"李老师不是你老师","accountId":"whyyoutouzhele","sensitive":false,"createdDate":"2024-08-05 17:08:34","content":"8月5日のニュースによると、日本株は12.4％急落し、台湾株は8.4％下落して過去最高値を記録したということで、その日「#A株のパフォーマンスは世界一#」という話題が熱い検索に殺到し、ネット民からの嘲笑を引き起こした。 。あるネチズンは、「私は何年転んだの？まだ言う勇気がある」と答えた。","images":"/tweet/image/whyyoutouzhele/2024/08/05/1820386404360446382_0.jpg,/tweet/image/whyyoutouzhele/2024/08/05/1820386404360446382_1.jpg,/tweet/image/whyyoutouzhele/2024/08/05/1820386404360446382_2.jpg,/tweet/image/whyyoutouzhele/2024/08/05/1820386404360446382_3.jpg,","videos":"","hasFullContentTranslated":true,"hasPublished":true},{"id":"1820389296152715343","name":"李老师不是你老师","accountId":"whyyoutouzhele","sensitive":false,"createdDate":"2024-08-05 17:20:04","content":"8月5日、江蘇省連雲港市。女性は実名で動画を投稿し、海州区書簡局局長の崔徳志氏に通報し、夫を殴ったと述べ、夫が殴られている動画を公開した。\n 現在、女性が投稿した通報動画は削除されている。 ","images":"/tweet/image/whyyoutouzhele/2024/08/05/1820389296152715343_0.jpg,","videos":"/tweet/video/whyyoutouzhele/2024/08/05/1820389296152715343_0.jpg,","hasFullContentTranslated":true,"hasPublished":true},{"id":"1820392844676251763","name":"李老师不是你老师","accountId":"whyyoutouzhele","sensitive":false,"createdDate":"2024-08-05 17:34:10","content":"8月5日（リリース）河北省保定市。長年にわたり法執行官を監督してきたブロガー「Xiao Ma Ge」は、都市管理者が道路脇にある業者の看板を差し押さえていることを発見し、ブロガーは都市管理者に法執行証明書と罰則用紙の提出を求めた。最終的に、ブロガーの助けで、業者は物を取り戻しました。業者は「（都市の管理者は）いつも人々をいじめます。今、普通の人々が生きていくのはどれほど難しいことでしょう！」と言いました。","images":"","videos":"/tweet/video/whyyoutouzhele/2024/08/05/1820392844676251763_0.jpg,","hasFullContentTranslated":true,"hasPublished":true},{"id":"1820396325025812627","name":"李老师不是你老师","accountId":"whyyoutouzhele","sensitive":false,"createdDate":"2024-08-05 17:47:59","content":"8月5日（公開）陝西省楡林市。この男は実名でビデオを送信し、紫州県工商連合会副会長の賈瑜氏が自分になりすまして学校に通っていたと報告した。 ","images":"","videos":"/tweet/video/whyyoutouzhele/2024/08/05/1820396325025812627_0.jpg,","hasFullContentTranslated":true,"hasPublished":true},{"id":"1820402123693302114","name":"李老师不是你老师","accountId":"whyyoutouzhele","sensitive":false,"createdDate":"2024-08-05 18:11:02","content":"飛翔.comの創設者、項立剛氏は8月3日、「当社に馬祥宇のような性格の人がいたら、間違いなく解雇する。そのような人物を会社に不安にさせてはいけない」と書いた。\n 現在、この投稿は削除されています。 ","images":"/tweet/image/whyyoutouzhele/2024/08/05/1820402123693302114_0.jpg,","videos":"","hasFullContentTranslated":true,"hasPublished":true},{"id":"1820408331472887962","name":"李老师不是你老师","accountId":"whyyoutouzhele","sensitive":false,"createdDate":"2024-08-05 18:35:42","content":"最近、オンライン法務論文のテーマには、刑事コンプライアンス、訴訟ソースの管理、積極的な司法、民間企業の平等な保護などを含めることはできないとの内部告発があったと一部のネチズンは述べた。 ","images":"/tweet/image/whyyoutouzhele/2024/08/05/1820408331472887962_0.jpg,/tweet/image/whyyoutouzhele/2024/08/05/1820408331472887962_1.jpg,/tweet/image/whyyoutouzhele/2024/08/05/1820408331472887962_2.jpg,/tweet/image/whyyoutouzhele/2024/08/05/1820408331472887962_3.jpg,","videos":"","hasFullContentTranslated":true,"hasPublished":true},{"id":"1820410945098629455","name":"李老师不是你老师","accountId":"whyyoutouzhele","sensitive":false,"createdDate":"2024-08-05 18:46:05","content":"8月5日、バングラデシュの学生運動の状況は大きく変化した。\nハシナ首相は辞任を発表し、妹とともにバングラデシュ空軍のヘリコプターでインドへ逃亡した。 ","images":"","videos":"/tweet/video/whyyoutouzhele/2024/08/05/1820410945098629455_0.jpg,","hasFullContentTranslated":true,"hasPublished":true},{"id":"1820412468843208953","name":"李老师不是你老师","accountId":"whyyoutouzhele","sensitive":false,"createdDate":"2024-08-05 18:52:08","content":"勝利後の学生らはハシナ首相の邸宅を襲撃し、ベッドに横たわった","images":"","videos":"/tweet/video/whyyoutouzhele/2024/08/05/1820412468843208953_0.jpg,","hasFullContentTranslated":true,"hasPublished":true},{"id":"1820414059843621307","name":"李老师不是你老师","accountId":"whyyoutouzhele","sensitive":false,"createdDate":"2024-08-05 18:58:28","content":"8月4日のニュースによると、復旦大学の著名教授である張偉未氏が著書「This is China: China’s Power Going Global」で今年の高等教育科学研究功績賞を受賞した。 ","images":"/tweet/image/whyyoutouzhele/2024/08/05/1820414059843621307_0.jpg,/tweet/image/whyyoutouzhele/2024/08/05/1820414059843621307_1.jpg,/tweet/image/whyyoutouzhele/2024/08/05/1820414059843621307_2.jpg,/tweet/image/whyyoutouzhele/2024/08/05/1820414059843621307_3.jpg,","videos":"","hasFullContentTranslated":true,"hasPublished":true},{"id":"1820425473547272332","name":"李老师不是你老师","accountId":"whyyoutouzhele","sensitive":false,"createdDate":"2024-08-05 19:43:49","content":"Big Vのブロガー、何光偉氏は、83歳の男性が裁判官を3時間侮辱したとして鄭州高新区人民法院から1万元の罰金を言い渡され、8月5日までに支払わなければならなかったと明らかにした。\n これに関連して、何光偉氏は「裁判官を侮辱した3時間のビデオを公開できるのか？この83歳の男性は1万元を持っているのか？」と語った。","images":"/tweet/image/whyyoutouzhele/2024/08/05/1820425473547272332_0.jpg,/tweet/image/whyyoutouzhele/2024/08/05/1820425473547272332_1.jpg,","videos":"","hasFullContentTranslated":true,"hasPublished":true},{"id":"1820432168390189431","name":"李老师不是你老师","accountId":"whyyoutouzhele","sensitive":false,"createdDate":"2024-08-05 20:10:25","content":"最近、雲南省のネットユーザーは、地方政府が発行する「中央農地肥沃度保護補助金」がわずか1.6元であることを明らかにした。広西チワン族自治区出身の別のネットユーザーは、合計20エーカー以上の土地に対して955元しか持っておらず、前年より半分以下になったと語った。 ","images":"/tweet/image/whyyoutouzhele/2024/08/05/1820432168390189431_0.jpg,/tweet/image/whyyoutouzhele/2024/08/05/1820432168390189431_1.jpg,/tweet/image/whyyoutouzhele/2024/08/05/1820432168390189431_2.jpg,/tweet/image/whyyoutouzhele/2024/08/05/1820432168390189431_3.jpg,","videos":"","hasFullContentTranslated":true,"hasPublished":true},{"id":"1820438029716332756","name":"李老师不是你老师","accountId":"whyyoutouzhele","sensitive":false,"createdDate":"2024-08-05 20:33:43","content":"8月5日のアップストリーム・ニュースの報道によると、通話の録音はインターネット上で拡散し、レイクさんは「私はどうして良心を犯したのか？私は彼女にお金を渡したのか？彼女は自発的にやったのだ」と答えたという。レイクは職務に関連した犯罪で起訴され、6か月前に捜査のために連行された。\n ","images":"/tweet/image/whyyoutouzhele/2024/08/05/1820438029716332756_0.jpg,","videos":"/tweet/video/whyyoutouzhele/2024/08/05/1820438029716332756_0.jpg,","hasFullContentTranslated":true,"hasPublished":true},{"id":"1820440873315741928","name":"李老师不是你老师","accountId":"whyyoutouzhele","sensitive":false,"createdDate":"2024-08-05 20:45:01","content":"7月16日、バングラデシュでの学生デモ中、警察は催涙ガスを発射し、警棒を使用して抗議する学生を解散させた。この間、アブ・サイードさんは両手を広げて銃に向かって一人取り残された。\n結局、警察はアブ・サイードさんを射殺し、彼は抗議活動の最初の犠牲者となった。\n死と対峙するアブの姿は、ますます多くのバングラデシュ人に街頭に繰り出すよう促し、勇気を与えた。彼を追悼するために、学生たちは彼が亡くなった交差点に彼の名前を付けました。","images":"","videos":"/tweet/video/whyyoutouzhele/2024/08/05/1820440873315741928_0.jpg,","hasFullContentTranslated":true,"hasPublished":true},{"id":"1820443982297542855","name":"李老师不是你老师","accountId":"whyyoutouzhele","sensitive":false,"createdDate":"2024-08-05 20:57:22","content":"ネチズンからの投稿\nタオバオの出品者は、自身の店舗が大規模な入金詐欺の被害に遭ったと述べた。出荷遅延に対する補償を申請する仕組みを利用して、販売者から保証金を騙し取るアカウントが多数存在します。インターネット上には、さまざまな「報酬を支払う」チュートリアルや求人広告も溢れています。この問題は、警察に電話したり、タオバオのカスタマーサービスに連絡したりしても効果的に対処できませんでした。\nソーシャルメディア上では、タオバオの出品者の多くが同じ詐欺被害に遭ったと述べている。 ","images":"/tweet/image/whyyoutouzhele/2024/08/05/1820443982297542855_0.jpg,/tweet/image/whyyoutouzhele/2024/08/05/1820443982297542855_1.jpg,/tweet/image/whyyoutouzhele/2024/08/05/1820443982297542855_2.jpg,/tweet/image/whyyoutouzhele/2024/08/05/1820443982297542855_3.jpg,","videos":"","hasFullContentTranslated":true,"hasPublished":true},{"id":"1820444341288010224","name":"李老师不是你老师","accountId":"whyyoutouzhele","sensitive":false,"createdDate":"2024-08-05 20:58:47","content":"バングラデシュ陸軍のワク・ウズ・ザマン総司令官は国民にテレビ演説し、シェイク・ハシナ首相が辞任し、暫定政府の樹立を発表したことを確認した。 ","images":"","videos":"/tweet/video/whyyoutouzhele/2024/08/05/1820444341288010224_0.jpg,","hasFullContentTranslated":true,"hasPublished":true},{"id":"1820444568439095309","name":"李老师不是你老师","accountId":"whyyoutouzhele","sensitive":false,"createdDate":"2024-08-05 20:59:41","content":"8月2日、住宅・都市農村開発部：住宅定期健康診断、住宅保険、住宅年金制度の構築を加速する。\n ネットユーザーは「将来は全員が健康診断を受ける必要がある。週に1回、毎回20元だ」「先生、私は住宅を登録したいのです」と答えた。","images":"/tweet/image/whyyoutouzhele/2024/08/05/1820444568439095309_0.jpg,/tweet/image/whyyoutouzhele/2024/08/05/1820444568439095309_1.jpg,/tweet/image/whyyoutouzhele/2024/08/05/1820444568439095309_2.jpg,","videos":"/tweet/video/whyyoutouzhele/2024/08/05/1820444568439095309_0.jpg,","hasFullContentTranslated":true,"hasPublished":true},{"id":"1820445982116442275","name":"李老师不是你老师","accountId":"whyyoutouzhele","sensitive":false,"createdDate":"2024-08-05 21:05:19","content":"https://t.co/4cdDsy69Xm","images":"","videos":"/tweet/video/whyyoutouzhele/2024/08/05/1820445982116442275_0.jpg,","hasPublished":true}]